kek/__init__.py
kek/check.py
kek/cli.py
kek/constants.py
kek/debug.py
kek/explain.py
kek/format.py
kek/hashing.py
kek/signature.py
kek/simulate.py
kek/utils.py
zerodev_kek-0.2.0.dist-info/licenses/LICENSE
zerodev_kek-0.2.0.dist-info/METADATA
zerodev_kek-0.2.0.dist-info/WHEEL
zerodev_kek-0.2.0.dist-info/entry_points.txt
zerodev_kek-0.2.0.dist-info/top_level.txt
zerodev_kek-0.2.0.dist-info/RECORD
